{
  "conditions": [
    {
      "type": "forge:and",
      "values": [
        {
          "type": "minecraft:item_exists",
          "item": "crazyae:mana_cell_1mb"
        },
        {
          "type": "appliedenergistics2:material_exists",
          "material": "material.empty_storage_cell"
        },
        {
          "type": "crazyae:material_exists",
          "name": "mana_part_1mb"
        }
      ]
    }
  ],
  "result": {
    "item": "crazyae:mana_cell_1mb"
  },
  "type": "forge:ore_shapeless",
  "ingredients": [
    {
      "type": "appliedenergistics2:part",
      "part": "material.empty_storage_cell"
    },
    {
      "type": "crazyae:material",
      "name": "mana_part_1mb"
    }
  ]
}
