{
  "conditions": [
    {
      "type": "forge:and",
      "values": [
        {
          "type": "minecraft:item_exists",
          "item": "crazyae:crafting_storage_4mb"
        },
        {
          "type": "minecraft:item_exists",
          "item": "appliedenergistics2:crafting_unit"
        },
        {
          "type": "crazyae:material_exists",
          "name": "cell_part_4mb"
        }
      ]
    }
  ],
  "result": {
    "item": "crazyae:crafting_storage_4mb"
  },
  "type": "forge:ore_shapeless",
  "ingredients": [
    {
      "item": "appliedenergistics2:crafting_unit"
    },
    {
      "type": "crazyae:material",
      "name": "cell_part_4mb"
    }
  ]
}
